format_service/__init__.py
format_service/format_service.py
request_service/__init__.py
request_service/city_requests.py
request_service/country_requests.py
python_package_lib-0.2.dist-info/METADATA
python_package_lib-0.2.dist-info/WHEEL
python_package_lib-0.2.dist-info/top_level.txt
python_package_lib-0.2.dist-info/RECORD
