Metadata-Version: 2.1
Name: python-package-lib
Version: 0.2
Requires-Dist: requests
